bibmancli/__init__.py
bibmancli/__main__.py
bibmancli/bibtex.py
bibmancli/cli.py
bibmancli/config_file.py
bibmancli/pdf_utils.py
bibmancli/resolve.py
bibmancli/tui.py
bibmancli/utils.py
bibmancli/version.py
bibmancli/subcommands/__init__.py
bibmancli/subcommands/check.py
bibmancli/subcommands/pdf.py
bibmancli-0.3.4.dist-info/METADATA
bibmancli-0.3.4.dist-info/WHEEL
bibmancli-0.3.4.dist-info/entry_points.txt
bibmancli-0.3.4.dist-info/licenses/LICENSE
bibmancli-0.3.4.dist-info/RECORD
