Metadata-Version: 2.3
Name: bibmancli
Version: 0.3.4
Summary: Simple CLI tool to manage BibTeX files.
Project-URL: Homepage, https://github.com/Parzival1918/bibman
Project-URL: Documentation, https://parzival1918.github.io/bibman/
Project-URL: Repository, https://github.com/Parzival1918/bibman
Author-email: Pedro Juan Royo <pedro.juan.royo@gmail.com>
License-Expression: MIT
License-File: LICENSE
Classifier: Environment :: Console
Classifier: Programming Language :: Python :: 3.11
Classifier: Programming Language :: Python :: 3.12
Classifier: Topic :: Utilities
Requires-Python: >=3.11
Requires-Dist: bibtexparser>=2.0.0b7
Requires-Dist: bs4>=0.0.2
Requires-Dist: habanero>=1.2.6
Requires-Dist: pyfzf-iter>=0.0.1
Requires-Dist: pylatexenc>=2.10
Requires-Dist: requests>=2.32.3
Requires-Dist: textual>=0.79.0
Requires-Dist: typer[all]>=0.12.4
